marshmallow_enum/__init__.py
marshmallow_enum-1.4.1.dist-info/DESCRIPTION.rst
marshmallow_enum-1.4.1.dist-info/METADATA
marshmallow_enum-1.4.1.dist-info/RECORD
marshmallow_enum-1.4.1.dist-info/WHEEL
marshmallow_enum-1.4.1.dist-info/metadata.json
marshmallow_enum-1.4.1.dist-info/top_level.txt
