Metadata-Version: 1.0
Name: marshmallow-enum
Version: 1.4.1
Summary: Enum field for Marshmallow
Home-page: UNKNOWN
Author: Alec Nikolas Reiter
Author-email: alecreiter@gmail.com
License: MIT
Platform: UNKNOWN
